boreal.libs/libgcc_s-b5472b99.so.1
boreal/__init__.py
boreal/__init__.pyi
boreal/boreal.abi3.so
boreal/py.typed
boreal_python-1.0.0.dist-info/METADATA
boreal_python-1.0.0.dist-info/WHEEL
boreal_python-1.0.0.dist-info/RECORD
