Metadata-Version: 2.4
Name: boreal-python
Version: 1.0.0
Summary: Python bindings to the boreal YARA scanner
Keywords: boreal,yara,string-matching,scan,python
Home-Page: https://github.com/vthib/boreal/
License: MIT OR Apache-2.0
Requires-Python: >=3.11
Project-URL: Source Code, https://github.com/vthib/boreal
